<?xml version="1.0" encoding="UTF-8"?>
<listing xmlns:xsi="http://www.w3.org/2001/XMLSchema-instance" xsi:noNamespaceSchemaLocation="urn:magento:module:Magento_Ui:etc/ui_configuration.xsd">
    <argument name="data" xsi:type="array">
        <item name="js_config" xsi:type="array">
            <item name="provider" xsi:type="string">import_listing.import_listing_data_source</item>
            <item name="deps" xsi:type="string">import_listing.import_listing_data_source</item>
        </item>
        <item name="spinner" xsi:type="string">import_columns</item>
    </argument>

    <dataSource name="import_listing_data_source">
        <argument name="dataProvider" xsi:type="configurableObject">
            <argument name="class" xsi:type="string">Magento\Framework\View\Element\UiComponent\DataProvider\DataProvider</argument>
            <argument name="name" xsi:type="string">import_listing_data_source</argument>
            <argument name="primaryFieldName" xsi:type="string">id</argument>
            <argument name="requestFieldName" xsi:type="string">id</argument>
            <argument name="data" xsi:type="array">
                <item name="config" xsi:type="array">
                    <item name="component" xsi:type="string">Magento_Ui/js/grid/provider</item>
                    <item name="update_url" xsi:type="url" path="mui/index/render"/>
                </item>
            </argument>
        </argument>
    </dataSource>

    <columns name="import_columns" class="Magento\Ui\Component\Listing\Columns">
        <column name="name">
            <argument name="data" xsi:type="array">
                <item name="config" xsi:type="array">
                    <item name="label" xsi:type="string" translate="true">Import Name</item>
                    <item name="sortOrder" xsi:type="number">20</item>

                </item>

            </argument>
        </column>

        <column name="type">
            <argument name="data" xsi:type="array">
                <item name="config" xsi:type="array">
                    <item name="label" xsi:type="string" translate="true">Import Type</item>
                    <item name="sortOrder" xsi:type="number">30</item>
                </item>
            </argument>
        </column>

        <column name="id_field">
            <argument name="data" xsi:type="array">
                <item name="config" xsi:type="array">
                    <item name="label" xsi:type="string" translate="true">ID Field</item>
                    <item name="sortOrder" xsi:type="number">40</item>
                </item>
            </argument>
        </column>

        <column name="indexers">
            <argument name="data" xsi:type="array">
                <item name="config" xsi:type="array">
                    <item name="label" xsi:type="string" translate="true">Indexers</item>
                    <item name="sortOrder" xsi:type="number">50</item>
                </item>
            </argument>
        </column>

        <column name="report_handlers">
            <argument name="data" xsi:type="array">
                <item name="config" xsi:type="array">
                    <item name="label" xsi:type="string" translate="true">Report Handlers</item>
                    <item name="sortOrder" xsi:type="number">60</item>
                </item>
            </argument>
        </column>

        <actionsColumn name="actions" class="Jh\Import\Ui\Component\Listing\Column\ImportConfigActions">
            <argument name="data" xsi:type="array">
                <item name="config" xsi:type="array">
                    <item name="indexField" xsi:type="string">id</item>
                    <item name="label" xsi:type="string" translate="true">Actions</item>
                </item>
            </argument>
        </actionsColumn>
    </columns>
</listing>